opc_conctrol_test/__init__.py
opc_conctrol_test-0.0.1.dist-info/LICENSE
opc_conctrol_test-0.0.1.dist-info/METADATA
opc_conctrol_test-0.0.1.dist-info/WHEEL
opc_conctrol_test-0.0.1.dist-info/top_level.txt
opc_conctrol_test-0.0.1.dist-info/RECORD
